loadbarpy.py
loadbarpy-1.0.0.dist-info/WHEEL
loadbarpy-1.0.0.dist-info/METADATA
loadbarpy-1.0.0.dist-info/RECORD
