Metadata-Version: 2.1
Name: loadbarpy
Version: 1.0.0
Summary: Cool loadbar for your python programs. Usage: LoadPy(\"nameofanimation\").animate() Animation names: default, miniload, bigload
Author: FreshHacks
Author-email: ddkkosta@gmail.com
Requires-Python: >=3.7,<4.0
Classifier: Programming Language :: Python :: 3
Classifier: Programming Language :: Python :: 3.7
Classifier: Programming Language :: Python :: 3.8
Classifier: Programming Language :: Python :: 3.9
